LICENSE
MANIFEST.in
README.rst
pyproject.toml
requirements.txt
setup.py
otree/__init__.py
otree/api.py
otree/api.pyi
otree/asgi.py
otree/auth.py
otree/chat.py
otree/checks.py
otree/common.py
otree/common2.py
otree/constants.py
otree/currency.py
otree/database.py
otree/decimal.py
otree/errorpage.py
otree/export.py
otree/i18n.py
otree/live.py
otree/lookup.py
otree/main.py
otree/middleware.py
otree/models_concrete.py
otree/mturk_client.py
otree/patch.py
otree/read_csv.py
otree/room.py
otree/session.py
otree/settings.py
otree/tasks.py
otree/test.py
otree/trials.py
otree/update.py
otree/urls.py
otree.egg-info/PKG-INFO
otree.egg-info/SOURCES.txt
otree.egg-info/dependency_links.txt
otree.egg-info/entry_points.txt
otree.egg-info/not-zip-safe
otree.egg-info/requires.txt
otree.egg-info/top_level.txt
otree/assets/__init__.py
otree/assets/__pycache__/__init__.cpython-310.pyc
otree/assets/__pycache__/__init__.cpython-311.pyc
otree/assets/app_template/MyPage.html
otree/assets/app_template/Results.html
otree/assets/app_template/__init__.py
otree/assets/app_template/__pycache__/__init__.cpython-310.pyc
otree/assets/app_template/__pycache__/__init__.cpython-311.pyc
otree/assets/app_template_trials/Results.html
otree/assets/app_template_trials/Task.html
otree/assets/app_template_trials/__init__.py
otree/assets/app_template_trials/trials.csv
otree/assets/app_template_trials/trials.js
otree/assets/app_template_trials/__pycache__/__init__.cpython-310.pyc
otree/assets/app_template_trials/__pycache__/__init__.cpython-311.pyc
otree/assets/project_template/.gitignore
otree/assets/project_template/Procfile
otree/assets/project_template/__init__.py
otree/assets/project_template/requirements.txt
otree/assets/project_template/settings.py
otree/assets/project_template/__pycache__/__init__.cpython-310.pyc
otree/assets/project_template/__pycache__/__init__.cpython-311.pyc
otree/assets/project_template/__pycache__/settings.cpython-310.pyc
otree/assets/project_template/__pycache__/settings.cpython-311.pyc
otree/assets/project_template/_static/global/empty.css
otree/bots/__init__.py
otree/bots/bot.py
otree/bots/browser.py
otree/bots/browser_launcher.py
otree/bots/runner.py
otree/channels/__init__.py
