Metadata-Version: 2.1
Name: otree
Version: 6.0.3
Summary: Framework for multiplayer strategy games and complex surveys.
Home-page: http://otree.org/
Author: chris@otree.org
Author-email: chris@otree.org
License: MIT License
Platform: UNKNOWN
Provides-Extra: mturk
License-File: LICENSE
